cw_pycon_8ball/__init__.py
cw_pycon_8ball/__main__.py
cw_pycon_8ball/words.txt
cw_pycon_8ball-0.0.2.data/scripts/8
cw_pycon_8ball-0.0.2.data/scripts/8ball
cw_pycon_8ball-0.0.2.data/scripts/ball
cw_pycon_8ball-0.0.2.dist-info/LICENSE
cw_pycon_8ball-0.0.2.dist-info/METADATA
cw_pycon_8ball-0.0.2.dist-info/WHEEL
cw_pycon_8ball-0.0.2.dist-info/entry_points.txt
cw_pycon_8ball-0.0.2.dist-info/top_level.txt
cw_pycon_8ball-0.0.2.dist-info/RECORD
