Metadata-Version: 2.1
Name: cw-pycon-8ball
Version: 0.0.2
Summary: 8ball for the terminal
Home-page: https://github.com/
Author: Cole Wilson
Author-email: cole@colewilson.xyz
License: MIT
Keywords: 8 ball 8ball magic terminal magical
Platform: UNKNOWN
Classifier: Programming Language :: Python :: 3
Requires-Python: >=3.6
